<?xml version="1.0" encoding="UTF-8"?>
<sbml xmlns="http://www.sbml.org/sbml/level3/version2/core" level="3" version="2">
  <model metaid="SOS_module" id="SOS_module" substanceUnits="substance" timeUnits="time_unit">
    <listOfFunctionDefinitions>
      <functionDefinition id="a">
        <math xmlns="http://www.w3.org/1998/Math/MathML">
          <lambda>
            <bvar>
              <ci> t </ci>
            </bvar>
            <apply>
              <minus/>
              <cn> 4.36776785714286 </cn>
              <apply>
                <times/>
                <cn type="integer"> 3 </cn>
                <cn> 0.165691964285714 </cn>
                <apply>
                  <power/>
                  <apply>
                    <minus/>
                    <ci> t </ci>
                    <cn type="integer"> 0 </cn>
                  </apply>
                  <cn type="integer"> 2 </cn>
                </apply>
              </apply>
            </apply>
          </lambda>
        </math>
      </functionDefinition>
      <functionDefinition id="b">
        <math xmlns="http://www.w3.org/1998/Math/MathML">
          <lambda>
            <bvar>
              <ci> t </ci>
            </bvar>
            <apply>
              <plus/>
              <apply>
                <minus/>
                <cn> 2.37946428571428 </cn>
                <apply>
                  <times/>
                  <cn type="integer"> 2 </cn>
                  <cn> 0.994151785714286 </cn>
                  <apply>
                    <minus/>
                    <ci> t </ci>
                    <cn type="integer"> 2 </cn>
                  </apply>
                </apply>
              </apply>
              <apply>
                <times/>
                <cn type="integer"> 3 </cn>
                <cn> 0.180959821428571 </cn>
                <apply>
                  <power/>
                  <apply>
                    <minus/>
                    <ci> t </ci>
                    <cn type="integer"> 2 </cn>
                  </apply>
                  <cn type="integer"> 2 </cn>
                </apply>
              </apply>
            </apply>
          </lambda>
        </math>
      </functionDefinition>
      <functionDefinition id="c">
        <math xmlns="http://www.w3.org/1998/Math/MathML">
          <lambda>
            <bvar>
              <ci> t </ci>
            </bvar>
            <apply>
              <minus/>
              <apply>
                <plus/>
                <cn> 0.574375 </cn>
                <apply>
                  <times/>
                  <cn type="integer"> 2 </cn>
                  <cn> 0.0916071428571431 </cn>
                  <apply>
                    <minus/>
                    <ci> t </ci>
                    <cn type="integer"> 4 </cn>
                  </apply>
                </apply>
              </apply>
              <apply>
                <times/>
                <cn type="integer"> 3 </cn>
                <cn> 0.0331473214285715 </cn>
                <apply>
                  <power/>
                  <apply>
                    <minus/>
                    <ci> t </ci>
                    <cn type="integer"> 4 </cn>
                  </apply>
                  <cn type="integer"> 2 </cn>
                </apply>
              </apply>
            </apply>
          </lambda>
        </math>
      </functionDefinition>
      <functionDefinition id="d">
        <math xmlns="http://www.w3.org/1998/Math/MathML">
          <lambda>
            <bvar>
              <ci> t </ci>
            </bvar>
            <apply>
              <plus/>
              <apply>
                <minus/>
                <cn> 0.543035714285715 </cn>
                <apply>
                  <times/>
                  <cn type="integer"> 2 </cn>
                  <cn> 0.107276785714286 </cn>
                  <apply>
                    <minus/>
                    <ci> t </ci>
                    <cn type="integer"> 6 </cn>
                  </apply>
                </apply>
              </apply>
              <apply>
                <times/>
                <cn type="integer"> 3 </cn>
                <cn> 0.0178794642857143 </cn>
                <apply>
                  <power/>
                  <apply>
                    <minus/>
                    <ci> t </ci>
                    <cn type="integer"> 6 </cn>
                  </apply>
                  <cn type="integer"> 2 </cn>
                </apply>
              </apply>
            </apply>
          </lambda>
        </math>
      </functionDefinition>
      <functionDefinition id="f">
        <math xmlns="http://www.w3.org/1998/Math/MathML">
          <lambda>
            <bvar>
              <ci> t </ci>
            </bvar>
            <cn> 0.328660937500002 </cn>
          </lambda>
        </math>
      </functionDefinition>
    </listOfFunctionDefinitions>
    <listOfUnitDefinitions>
      <unitDefinition id="substance">
        <listOfUnits>
          <unit kind="mole" exponent="1" scale="-9" multiplier="1"/>
        </listOfUnits>
      </unitDefinition>
      <unitDefinition id="time_unit">
        <listOfUnits>
          <unit kind="second" exponent="1" scale="0" multiplier="1"/>
        </listOfUnits>
      </unitDefinition>
      <unitDefinition id="nM">
        <listOfUnits>
          <unit kind="mole" exponent="1" scale="-9" multiplier="1"/>
          <unit kind="litre" exponent="-1" scale="0" multiplier="1"/>
        </listOfUnits>
      </unitDefinition>
      <unitDefinition id="per_nM">
        <listOfUnits>
          <unit kind="litre" exponent="1" scale="0" multiplier="1"/>
          <unit kind="mole" exponent="-1" scale="-9" multiplier="1"/>
        </listOfUnits>
      </unitDefinition>
      <unitDefinition id="per_sec">
        <listOfUnits>
          <unit kind="second" exponent="-1" scale="0" multiplier="1"/>
        </listOfUnits>
      </unitDefinition>
      <unitDefinition id="nM_per_sec">
        <listOfUnits>
          <unit kind="mole" exponent="1" scale="-9" multiplier="1"/>
          <unit kind="litre" exponent="-1" scale="0" multiplier="1"/>
          <unit kind="second" exponent="-1" scale="0" multiplier="1"/>
        </listOfUnits>
      </unitDefinition>
      <unitDefinition id="per_nMs">
        <listOfUnits>
          <unit kind="litre" exponent="1" scale="0" multiplier="1"/>
          <unit kind="mole" exponent="-1" scale="-9" multiplier="1"/>
          <unit kind="second" exponent="-1" scale="0" multiplier="1"/>
        </listOfUnits>
      </unitDefinition>
    </listOfUnitDefinitions>
    <listOfCompartments>
      <compartment sboTerm="SBO:0000410" id="default_compartment" spatialDimensions="3" size="1" constant="true"/>
      <compartment id="cell" spatialDimensions="3" size="1" constant="true"/>
      <compartment id="extra" spatialDimensions="3" size="5000" constant="true"/>
      <compartment id="intra" spatialDimensions="3" size="1" constant="true"/>
    </listOfCompartments>
    <listOfSpecies>
      <species id="Gab1_pShp2" compartment="default_compartment" initialAmount="0" hasOnlySubstanceUnits="false" boundaryCondition="false" constant="false"/>
      <species id="Garem_pShp2" compartment="default_compartment" initialAmount="0" hasOnlySubstanceUnits="false" boundaryCondition="false" constant="false"/>
      <species id="pShc1" compartment="default_compartment" initialAmount="0" hasOnlySubstanceUnits="false" boundaryCondition="false" constant="false"/>
      <species id="aRtot" compartment="default_compartment" initialConcentration="0" hasOnlySubstanceUnits="false" boundaryCondition="true" constant="false"/>
      <species id="Sos1Ihtr" compartment="cell" initialConcentration="1" hasOnlySubstanceUnits="false" boundaryCondition="true" constant="false"/>
      <species id="Grb2" compartment="cell" initialAmount="0" hasOnlySubstanceUnits="false" boundaryCondition="false" constant="false"/>
      <species id="SOS1" compartment="default_compartment" initialAmount="0" hasOnlySubstanceUnits="false" boundaryCondition="false" constant="false"/>
      <species id="Grb2_SOS1" compartment="default_compartment" initialAmount="6.2" hasOnlySubstanceUnits="false" boundaryCondition="false" constant="false"/>
      <species id="Grb2_pSOS1" compartment="default_compartment" initialAmount="0" hasOnlySubstanceUnits="false" boundaryCondition="false" constant="false"/>
      <species id="Grb2_ipSOS1" compartment="cell" initialAmount="0" hasOnlySubstanceUnits="false" boundaryCondition="false" constant="false"/>
      <species id="aAdptrTot" compartment="default_compartment" initialAmount="2.06" hasOnlySubstanceUnits="false" boundaryCondition="false" constant="false"/>
      <species id="dRas" compartment="default_compartment" initialAmount="98" hasOnlySubstanceUnits="false" boundaryCondition="false" constant="false"/>
      <species id="tRas" compartment="default_compartment" initialAmount="0" hasOnlySubstanceUnits="false" boundaryCondition="false" constant="false"/>
    </listOfSpecies>
    <listOfParameters>
      <parameter id="kcat2" value="0.527198424391686" constant="true"/>
      <parameter id="Km2" value="0.212652830057631" constant="true"/>
      <parameter id="kcat3" value="9.99997420556397" constant="true"/>
      <parameter id="Km3" value="7.71807636063192" constant="true"/>
      <parameter id="aSOS" value="0" constant="false"/>
      <parameter id="ktRas" value="4.43644093611311" constant="true"/>
      <parameter id="KmRasd" value="1.13246870942622" constant="true"/>
      <parameter id="kdRas" value="0.740149141914273" constant="true"/>
      <parameter id="GAP" value="1" constant="true"/>
      <parameter id="KmRast" value="0.134574607224175" constant="true"/>
    </listOfParameters>
    <listOfRules>
      <assignmentRule variable="aSOS">
        <math xmlns="http://www.w3.org/1998/Math/MathML">
          <ci> Grb2_pSOS1 </ci>
        </math>
      </assignmentRule>
    </listOfRules>
    <listOfReactions>
      <reaction id="J0" reversible="true">
        <listOfProducts>
          <speciesReference species="aAdptrTot" stoichiometry="1" constant="true"/>
        </listOfProducts>
        <kineticLaw>
          <math xmlns="http://www.w3.org/1998/Math/MathML">
            <piecewise>
              <piece>
                <apply>
                  <ci> a </ci>
                  <csymbol encoding="text" definitionURL="http://www.sbml.org/sbml/symbols/time"> time </csymbol>
                </apply>
                <apply>
                  <leq/>
                  <csymbol encoding="text" definitionURL="http://www.sbml.org/sbml/symbols/time"> time </csymbol>
                  <cn type="integer"> 2 </cn>
                </apply>
              </piece>
              <piece>
                <apply>
                  <ci> b </ci>
                  <csymbol encoding="text" definitionURL="http://www.sbml.org/sbml/symbols/time"> time </csymbol>
                </apply>
                <apply>
                  <leq/>
                  <csymbol encoding="text" definitionURL="http://www.sbml.org/sbml/symbols/time"> time </csymbol>
                  <cn type="integer"> 4 </cn>
                </apply>
              </piece>
              <piece>
                <apply>
                  <ci> c </ci>
                  <csymbol encoding="text" definitionURL="http://www.sbml.org/sbml/symbols/time"> time </csymbol>
                </apply>
                <apply>
                  <leq/>
                  <csymbol encoding="text" definitionURL="http://www.sbml.org/sbml/symbols/time"> time </csymbol>
                  <cn type="integer"> 6 </cn>
                </apply>
              </piece>
              <piece>
                <apply>
                  <ci> d </ci>
                  <csymbol encoding="text" definitionURL="http://www.sbml.org/sbml/symbols/time"> time </csymbol>
                </apply>
                <apply>
                  <leq/>
                  <csymbol encoding="text" definitionURL="http://www.sbml.org/sbml/symbols/time"> time </csymbol>
                  <cn type="integer"> 8 </cn>
                </apply>
              </piece>
              <piece>
                <apply>
                  <ci> f </ci>
                  <csymbol encoding="text" definitionURL="http://www.sbml.org/sbml/symbols/time"> time </csymbol>
                </apply>
                <apply>
                  <leq/>
                  <csymbol encoding="text" definitionURL="http://www.sbml.org/sbml/symbols/time"> time </csymbol>
                  <cn type="integer"> 10 </cn>
                </apply>
              </piece>
            </piecewise>
          </math>
        </kineticLaw>
      </reaction>
      <reaction id="J2" reversible="true">
        <listOfReactants>
          <speciesReference species="aAdptrTot" stoichiometry="1" constant="true"/>
          <speciesReference species="Grb2_SOS1" stoichiometry="1" constant="true"/>
        </listOfReactants>
        <listOfProducts>
          <speciesReference species="aAdptrTot" stoichiometry="1" constant="true"/>
          <speciesReference species="Grb2_pSOS1" stoichiometry="1" constant="true"/>
        </listOfProducts>
        <kineticLaw>
          <math xmlns="http://www.w3.org/1998/Math/MathML">
            <apply>
              <divide/>
              <apply>
                <times/>
                <ci> kcat2 </ci>
                <ci> aAdptrTot </ci>
                <ci> Grb2_SOS1 </ci>
              </apply>
              <apply>
                <plus/>
                <ci> Km2 </ci>
                <ci> Grb2_SOS1 </ci>
              </apply>
            </apply>
          </math>
        </kineticLaw>
      </reaction>
      <reaction id="J3" reversible="true">
        <listOfReactants>
          <speciesReference species="Sos1Ihtr" stoichiometry="1" constant="true"/>
          <speciesReference species="Grb2_pSOS1" stoichiometry="1" constant="true"/>
        </listOfReactants>
        <listOfProducts>
          <speciesReference species="Sos1Ihtr" stoichiometry="1" constant="true"/>
          <speciesReference species="Grb2_ipSOS1" stoichiometry="1" constant="true"/>
        </listOfProducts>
        <kineticLaw>
          <math xmlns="http://www.w3.org/1998/Math/MathML">
            <apply>
              <divide/>
              <apply>
                <times/>
                <ci> kcat3 </ci>
                <ci> Sos1Ihtr </ci>
                <ci> Grb2_pSOS1 </ci>
              </apply>
              <apply>
                <plus/>
                <ci> Km3 </ci>
                <ci> Grb2_pSOS1 </ci>
              </apply>
            </apply>
          </math>
        </kineticLaw>
      </reaction>
      <reaction id="J5" reversible="false">
        <listOfReactants>
          <speciesReference species="dRas" stoichiometry="1" constant="true"/>
        </listOfReactants>
        <listOfProducts>
          <speciesReference species="tRas" stoichiometry="1" constant="true"/>
        </listOfProducts>
        <kineticLaw>
          <math xmlns="http://www.w3.org/1998/Math/MathML">
            <apply>
              <divide/>
              <apply>
                <times/>
                <ci> ktRas </ci>
                <ci> dRas </ci>
                <ci> aSOS </ci>
              </apply>
              <apply>
                <plus/>
                <ci> KmRasd </ci>
                <ci> dRas </ci>
              </apply>
            </apply>
          </math>
        </kineticLaw>
      </reaction>
      <reaction id="J6" reversible="false">
        <listOfReactants>
          <speciesReference species="tRas" stoichiometry="1" constant="true"/>
        </listOfReactants>
        <listOfProducts>
          <speciesReference species="dRas" stoichiometry="1" constant="true"/>
        </listOfProducts>
        <kineticLaw>
          <math xmlns="http://www.w3.org/1998/Math/MathML">
            <apply>
              <divide/>
              <apply>
                <times/>
                <ci> kdRas </ci>
                <ci> tRas </ci>
                <ci> GAP </ci>
              </apply>
              <apply>
                <plus/>
                <ci> KmRast </ci>
                <ci> tRas </ci>
              </apply>
            </apply>
          </math>
        </kineticLaw>
      </reaction>
    </listOfReactions>
  </model>
</sbml>
